scrapdynamics/__init__.py
scrapdynamics/__main__.py
scrapdynamics/crawler.py
scrapdynamics/progressbar.py
scrapdynamics/settings.py
scrapdynamics/url.py
scrapdynamics-0.2.0.dist-info/LICENSE
scrapdynamics-0.2.0.dist-info/METADATA
scrapdynamics-0.2.0.dist-info/WHEEL
scrapdynamics-0.2.0.dist-info/top_level.txt
scrapdynamics-0.2.0.dist-info/RECORD
