Metadata-Version: 2.1
Name: scrapdynamics
Version: 0.2.0
Summary: ScrapDynamics is a powerful framework for exploring and crawling websites.
Home-page: https://github.com/guychahine/scrapdynamics
Author: Guy Chahine
Author-email: guychahine@gmail.com
License: BSD
Platform: UNKNOWN
Classifier: Development Status :: 5 - Production/Stable
Classifier: Intended Audience :: Developers
Classifier: License :: OSI Approved :: BSD License
Classifier: Operating System :: OS Independent
Classifier: Programming Language :: Python
Classifier: Programming Language :: Python :: 3
Classifier: Programming Language :: Python :: 3.9
Classifier: Programming Language :: Python :: 3.10
Classifier: Programming Language :: Python :: 3.11
Classifier: Programming Language :: Python :: 3 :: Only
Classifier: Programming Language :: Python :: Implementation :: CPython
Classifier: Programming Language :: Python :: Implementation :: PyPy
Classifier: Topic :: Internet :: WWW/HTTP
Classifier: Topic :: Software Development :: Libraries :: Application Frameworks
Classifier: Topic :: Software Development :: Libraries :: Python Modules
Requires-Python: >=3.9
License-File: LICENSE
Requires-Dist: lxml (>=4.9.2)
Requires-Dist: pandas (>=2.0.2)
Requires-Dist: requests (>=2.31.0)
Requires-Dist: rich (>=13.4.2)
Requires-Dist: selenium (>=4.10.0)
